netpicker_cli/HTTP_API.md
netpicker_cli/__init__.py
netpicker_cli/cli.py
netpicker_cli/api/client.py
netpicker_cli/api/errors.py
netpicker_cli/commands/auth.py
netpicker_cli/commands/automation.py
netpicker_cli/commands/backups.py
netpicker_cli/commands/compliance.py
netpicker_cli/commands/compliance_policy.py
netpicker_cli/commands/devices.py
netpicker_cli/commands/health.py
netpicker_cli/commands/whoami.py
netpicker_cli/mcp/README.md
netpicker_cli/mcp/__init__.py
netpicker_cli/mcp/claude-desktop-config.json
netpicker_cli/mcp/server.py
netpicker_cli/utils/cache.py
netpicker_cli/utils/cli_helpers.py
netpicker_cli/utils/command_base.py
netpicker_cli/utils/config.py
netpicker_cli/utils/config_extraction.py
netpicker_cli/utils/files.py
netpicker_cli/utils/helpers.py
netpicker_cli/utils/logging.py
netpicker_cli/utils/output.py
netpicker_cli/utils/pagination.py
netpicker_cli/utils/validation.py
netpicker_cli-0.1.10.dist-info/licenses/LICENSE
netpicker_cli-0.1.10.dist-info/METADATA
netpicker_cli-0.1.10.dist-info/WHEEL
netpicker_cli-0.1.10.dist-info/entry_points.txt
netpicker_cli-0.1.10.dist-info/top_level.txt
netpicker_cli-0.1.10.dist-info/RECORD
