Metadata-Version: 2.4
Name: netpicker-cli
Version: 0.1.10
Summary: Netpicker CLI for devices and backups
Author-email: Netpicker Team <support@netpicker.io>
License-Expression: MIT
Project-URL: Homepage, https://netpicker.io
Project-URL: Documentation, https://github.com/netpicker/netpicker-cli#readme
Project-URL: Repository, https://github.com/netpicker/netpicker-cli
Project-URL: Issues, https://github.com/netpicker/netpicker-cli/issues
Project-URL: Changelog, https://github.com/netpicker/netpicker-cli/blob/main/CHANGELOG.md
Keywords: netpicker,network,cli,automation,configuration,backup
Classifier: Development Status :: 4 - Beta
Classifier: Environment :: Console
Classifier: Intended Audience :: System Administrators
Classifier: Intended Audience :: Developers
Classifier: Operating System :: OS Independent
Classifier: Programming Language :: Python :: 3
Classifier: Programming Language :: Python :: 3.11
Classifier: Programming Language :: Python :: 3.12
Classifier: Topic :: System :: Networking
Classifier: Topic :: System :: Systems Administration
Requires-Python: >=3.11
License-File: LICENSE
Requires-Dist: typer>=0.12.5
Requires-Dist: mcp>=1.0.0
Requires-Dist: httpx>=0.27
Requires-Dist: pydantic>=2.8
Requires-Dist: keyring>=25.2.1
Requires-Dist: python-dotenv>=1.0.1
Requires-Dist: tabulate>=0.9.0
Requires-Dist: PyYAML>=6.0.1
Provides-Extra: dev
Requires-Dist: pytest>=8; extra == "dev"
Requires-Dist: respx>=0.21.1; extra == "dev"
Requires-Dist: pytest-cov>=5; extra == "dev"
Requires-Dist: hypothesis>=6; extra == "dev"
Requires-Dist: ruff>=0.6; extra == "dev"
Requires-Dist: black>=24; extra == "dev"
Requires-Dist: mypy>=1.11; extra == "dev"
Requires-Dist: types-tabulate>=0.9.0.20240106; extra == "dev"
Dynamic: license-file
